plsc/__init__.py
plsc/core/__init__.py
plsc/core/grad_clip.py
plsc/core/grad_scaler.py
plsc/core/param_fuse.py
plsc/core/recompute.py
plsc/core/sync_utils.py
plsc/data/__init__.py
plsc/data/dataset/__init__.py
plsc/data/dataset/common_dataset.py
plsc/data/dataset/face_recognition_dataset.py
plsc/data/dataset/imagefolder_dataset.py
plsc/data/dataset/imagenet_dataset.py
plsc/data/postprocess/__init__.py
plsc/data/preprocess/__init__.py
plsc/data/preprocess/basic_transforms.py
plsc/data/preprocess/batch_transforms.py
plsc/data/preprocess/timm_autoaugment.py
plsc/data/sampler/__init__.py
plsc/data/sampler/repeatedaug_sampler.py
plsc/data/utils/__init__.py
plsc/data/utils/batch_collate_fn.py
plsc/data/utils/transform_utils.py
plsc/engine/__init__.py
plsc/engine/engine.py
plsc/engine/inference.py
plsc/engine/classification/__init__.py
plsc/engine/classification/evaluation.py
plsc/engine/classification/train.py
plsc/engine/classification/utils.py
plsc/engine/recognition/__init__.py
plsc/engine/recognition/evaluation.py
plsc/engine/recognition/train.py
plsc/engine/recognition/utils.py
plsc/loss/__init__.py
plsc/loss/celoss.py
plsc/loss/marginloss.py
plsc/metric/__init__.py
plsc/metric/lfw_utils.py
plsc/metric/metrics.py
plsc/models/__init__.py
plsc/models/base_model.py
plsc/models/cait.py
plsc/models/deit.py
plsc/models/face_vit.py
plsc/models/iresnet.py
plsc/models/mobilefacenet.py
plsc/models/vision_transformer.py
plsc/nn/__init__.py
plsc/nn/init.py
plsc/nn/norm.py
plsc/nn/partialfc.py
plsc/optimizer/__init__.py
plsc/optimizer/adafactor.py
plsc/optimizer/adamw.py
plsc/optimizer/momentum.py
plsc/optimizer/momentum_lars.py
plsc/optimizer/optimizer.py
plsc/scheduler/__init__.py
plsc/scheduler/lr_scheduler.py
plsc/utils/__init__.py
plsc/utils/config.py
plsc/utils/io.py
plsc/utils/logger.py
plsc/utils/misc.py
plsc/utils/profiler.py
plsc-2.4.0.dist-info/LICENSE
plsc-2.4.0.dist-info/METADATA
plsc-2.4.0.dist-info/WHEEL
plsc-2.4.0.dist-info/entry_points.txt
plsc-2.4.0.dist-info/top_level.txt
plsc-2.4.0.dist-info/RECORD
