Metadata-Version: 2.1
Name: plsc
Version: 2.4.0
Summary: PLSC is an open source repo for a collection of Paddle Large Scale Classification Tools, which supports large-scale classification model pre-training as well as finetune for downstream tasks.
Home-page: https://github.com/PaddlePaddle/PLSC
Download-URL: https://github.com/PaddlePaddle/PLSC.git
Author: PLSC Contributors
Keywords: face-recognition,vision-classification,large-scale,distributed-training,data-parallel,model-parallel,resnet,vit,face-vit,deit,partial-fc,arcface
Classifier: Intended Audience :: Developers
Classifier: Intended Audience :: Science/Research
Classifier: License :: OSI Approved :: Apache Software License
Classifier: Programming Language :: Python :: 3.7
Classifier: Topic :: Scientific/Engineering :: Artificial Intelligence
License-File: LICENSE
Requires-Dist: pillow
Requires-Dist: numpy
Requires-Dist: easydict
Requires-Dist: scikit-image
Requires-Dist: scipy
Requires-Dist: sklearn
Requires-Dist: requests
Requires-Dist: prettytable
Requires-Dist: tqdm
Requires-Dist: visualdl
Requires-Dist: scikit-learn (>=0.23.2)
Requires-Dist: opencv-python (>=4.2.0.32)
Requires-Dist: onnxruntime-gpu (==1.10.0)
Requires-Dist: onnx (==1.9.0)
Requires-Dist: paddle2onnx (==0.9.4)
